flake8_custom_error_messages/__init__.py
flake8_custom_error_messages/plugin.py
flake8_custom_error_messages-0.1.1.dist-info/entry_points.txt
flake8_custom_error_messages-0.1.1.dist-info/LICENSE
flake8_custom_error_messages-0.1.1.dist-info/WHEEL
flake8_custom_error_messages-0.1.1.dist-info/METADATA
flake8_custom_error_messages-0.1.1.dist-info/RECORD
