Metadata-Version: 2.1
Name: flake8-custom-error-messages
Version: 0.1.1
Summary: A flake8 plugin to customize the error messages emitted by other flake8 plugins
Keywords: flake8,flake8 plugin,custom error messages
Author: Ghazi Abbassi
Requires-Python: >=3.8
Classifier: Intended Audience :: Developers
Classifier: License :: OSI Approved :: MIT License
Classifier: Programming Language :: Python :: 3
Classifier: Programming Language :: Python :: 3.8
Classifier: Programming Language :: Python :: 3.9
Classifier: Programming Language :: Python :: 3.10
Classifier: Programming Language :: Python :: 3.11
Requires-Dist: flake8
Requires-Dist: pre-commit ; extra == "dev"
Requires-Dist: flit ; extra == "release"
Requires-Dist: keyring ; extra == "release"
Requires-Dist: tbump ; extra == "release"
Project-URL: Changelog, https://github.com/ghazi-git/flake8-custom-error-messages/releases
Project-URL: Code, https://github.com/ghazi-git/flake8-custom-error-messages
Project-URL: Issues, https://github.com/ghazi-git/flake8-custom-error-messages/issues
Provides-Extra: dev
Provides-Extra: release
